{
  "text_id": "oracc.etcsri.Q001683",
  "corpus": "oracc",
  "title": "Šulgi 51 (RIME 3/2.01.02.051 composite)",
  "language": "sumerian",
  "translation_source": "ORACC ETCSRI — CC BY-SA 3.0",
  "source_url": "https://oracc.museum.upenn.edu/etcsri/Q001683",
  "paragraphs": [
    {
      "para_id": "Q001683.1",
      "line_range": "1",
      "translation": "(1) For Nanna , his master , Šulgi , the powerful man , king of Urim , king of the four quarters , certified this ( weight stone to be ) 2 manas."
    }
  ],
  "lines": [
    {
      "line_id": "Q001683.1",
      "line_label": "1",
      "transliteration": "d nanna"
    },
    {
      "line_id": "Q001683.2",
      "line_label": "2",
      "transliteration": "lugal - a - ni"
    },
    {
      "line_id": "Q001683.3",
      "line_label": "3",
      "transliteration": "d šul - gi"
    },
    {
      "line_id": "Q001683.4",
      "line_label": "4",
      "transliteration": "nita kalag - ga"
    },
    {
      "line_id": "Q001683.5",
      "line_label": "5",
      "transliteration": "lugal urim₅ ki - ma"
    },
    {
      "line_id": "Q001683.6",
      "line_label": "6",
      "transliteration": "lugal an - ub - da limmu₂ - ba - ke₄"
    },
    {
      "line_id": "Q001683.7",
      "line_label": "7",
      "transliteration": "2( diš ) ma - na"
    },
    {
      "line_id": "Q001683.8",
      "line_label": "8",
      "transliteration": "mu - na - ge - en₆"
    }
  ]
}