{
  "text_id": "oracc.etcsri.Q003656",
  "corpus": "oracc",
  "title": "Ur-LUM-ma 2 (RIME 1.12.04.02 composite)",
  "language": "sumerian",
  "translation_source": "ORACC ETCSRI — CC BY-SA 3.0",
  "source_url": "https://oracc.museum.upenn.edu/etcsri/Q003656",
  "paragraphs": [
    {
      "para_id": "Q003656.1",
      "line_range": "1",
      "translation": "(1) For Nagarpae , Ur-Luma , king of Umma , child of En-akale , king of Umma , built his temple ."
    }
  ],
  "lines": [
    {
      "line_id": "Q003656.1",
      "line_label": "1",
      "transliteration": "d nagar - pa - e₃"
    },
    {
      "line_id": "Q003656.2",
      "line_label": "2",
      "transliteration": "ur - d lum - ma"
    },
    {
      "line_id": "Q003656.3",
      "line_label": "3",
      "transliteration": "lugal umma₂"
    },
    {
      "line_id": "Q003656.4",
      "line_label": "4",
      "transliteration": "dumu en - a₂ - kal - le"
    },
    {
      "line_id": "Q003656.5",
      "line_label": "5",
      "transliteration": "lugal umma₂"
    },
    {
      "line_id": "Q003656.6",
      "line_label": "6",
      "transliteration": "e₂ - ni e - na - du₃"
    }
  ]
}